<?xml version="1.0" encoding="UTF-8"?>
<!DOCTYPE sect1 PUBLIC "-//OASIS//DTD DocBook XML V4.5//EN"
   "http://www.oasis-open.org/docbook/xml/4.5/docbookx.dtd" [
  <!ENTITY % general-entities SYSTEM "../../general.ent">
  %general-entities;

  <!ENTITY wev-download-http "https://git.sr.ht/~sircmpwn/wev/archive/&wev-version;.tar.gz">
]>

<sect1 id="wev" xreflabel="wev-&wev-version;">
  <?dbhtml filename="wev.html"?>

  <title>wev-&wev-version;</title>

  <indexterm zone="wev">
    <primary sortas="a-wev">wev</primary>
  </indexterm>

  <sect2 role="package">
    <title>Introduction to wev</title>

    <para>
      The wev package contains a utility to show Wayland events.
    </para>

    <itemizedlist spacing="compact">
      <listitem>
        <para>
          Download (HTTP): <ulink url="&wev-download-http;"/>
        </para>
      </listitem>
    </itemizedlist>

    <bridgehead renderas="sect3">wev Dependencies</bridgehead>

    <bridgehead renderas="sect4">Required</bridgehead>
    <para role="required">
      <ulink url="&blfs-svn;/general/libxkbcommon.html">libxkbcommon</ulink>,
      <xref linkend="scdoc"/>,
      <ulink url="&blfs-svn;/general/wayland.html">Wayland</ulink>, and
      <ulink url="&blfs-svn;/general/wayland-protocols.html">Wayland-Protocols</ulink>
    </para>

  </sect2>

  <sect2 role="installation">
    <title>Installation of wev</title>

    <para>
      Install wev by executing the following commands:
    </para>

<screen><userinput>make</userinput></screen>

    <para>
      Now as the &root; user:
    </para>

<screen role="root"><userinput>make PREFIX=/usr install</userinput></screen>

  </sect2>

  <sect2 role="content">
    <title>Contents</title>

    <segmentedlist>
      <segtitle>Installed Programs</segtitle>
      <segtitle>Installed Libraries</segtitle>
      <segtitle>Installed Directories</segtitle>

      <seglistitem>
        <seg>
          wev
        </seg>
        <seg>
          None
        </seg>
        <seg>
          None
        </seg>
      </seglistitem>
    </segmentedlist>

    <variablelist>
      <bridgehead renderas="sect3">Short Descriptions</bridgehead>
      <?dbfo list-presentation="list"?>
      <?dbhtml list-presentation="table"?>

      <varlistentry id="wev-bin">
        <term><command>wev</command></term>
        <listitem>
          <para>
            is a Wayland event tracker
          </para>
          <indexterm zone="wev wev-bin">
            <primary sortas="b-wev-bin">wev</primary>
          </indexterm>
        </listitem>
      </varlistentry>

    </variablelist>

  </sect2>

</sect1>
