<?xml version="1.0" encoding="UTF-8"?>
<!DOCTYPE sect1 PUBLIC "-//OASIS//DTD DocBook XML V4.5//EN"
   "http://www.oasis-open.org/docbook/xml/4.5/docbookx.dtd" [
  <!ENTITY % general-entities SYSTEM "../general.ent">
  %general-entities;

  <!ENTITY hyprwayland-scanner-download-http "https://github.com/hyprwm/hyprwayland-scanner/archive/refs/tags/v&hyprwayland-scanner-version;.tar.gz">
]>

<sect1 id="hyprwayland-scanner" xreflabel="hyprwayland-scanner-&hyprwayland-scanner-version;">
  <?dbhtml filename="hyprwayland-scanner.html"?>


  <title>hyprwayland-scanner-&hyprwayland-scanner-version;</title>

  <indexterm zone="hyprwayland-scanner">
    <primary sortas="a-hyprwayland-scanner">hyprwayland-scanner</primary>
  </indexterm>

  <sect2 role="package">
    <title>Introduction to hyprwayland-scanner</title>

    <para>
      The hyprwayland-scanner package provides a Hyprland-specific
      implementation of <command>wayland-scanner</command> provided by the
      <ulink url="&blfs-svn;/general/wayland-protocols.html">Wayland-Protocols</ulink>
      package.
    </para>

    <bridgehead renderas="sect3">Package Information</bridgehead>
    <itemizedlist spacing="compact">
      <listitem>
        <para>
          Download (HTTP): <ulink url="&hyprwayland-scanner-download-http;"/>
        </para>
      </listitem>
    </itemizedlist>

    <bridgehead renderas="sect3">hyprwayland-scanner Dependencies</bridgehead>

    <bridgehead renderas="sect4">Required</bridgehead>
    <para role="required">
      <ulink url="&blfs-svn;/general/cmake.html">CMake</ulink> and
      <xref linkend="pugixml"/>
    </para>

  </sect2>

  <sect2 role="installation">
    <title>Installation of hyprwayland-scanner</title>

    <para>
      Install <application>hyprwayland-scanner</application> by running the following
      commands:
    </para>

<screen><userinput>mkdir build &amp;&amp;
cd    build &amp;&amp;

cmake -D CMAKE_INSTALL_PREFIX=/usr   \
      -D CMAKE_BUILD_TYPE=Release    \
      -D CMAKE_SKIP_INSTALL_RPATH=ON \
      -G Ninja .. &amp;&amp;

ninja</userinput></screen>

    <para>
      Now, as the &root; user:
    </para>

<screen role="root"><userinput>ninja install</userinput></screen>

  </sect2>
  
  <sect2 role="commands">
    <title>Command Explanations</title>

    <xi:include xmlns:xi="http://www.w3.org/2001/XInclude"
      href="../xincludes/cmake-skip-install-rpath.xml"/>

  </sect2>

  <sect2 role="content">
    <title>Contents</title>

    <segmentedlist>
      <segtitle>Installed Programs</segtitle>
      <segtitle>Installed Libraries</segtitle>
      <segtitle>Installed Directories</segtitle>

      <seglistitem>
        <seg>
          hyprwayland-scanner
        </seg>
        <seg>
          None
        </seg>
        <seg>
          /usr/lib/cmake/hyprwayland-scanner
        </seg>
      </seglistitem>
    </segmentedlist>

    <variablelist>
      <bridgehead renderas="sect3">Short Descriptions</bridgehead>
      <?dbfo list-presentation="list"?>
      <?dbhtml list-presentation="table"?>

      <varlistentry id="hyprwayland-scanner-bin">
        <term><command>hyprwayland-scanner</command></term>
        <listitem>
          <para>
            generates C++ code from <application>Wayland</application> protocol
            XML files
          </para>
          <indexterm zone="hyprwayland-scanner hyprwayland-scanner-bin">
            <primary sortas="b-hyprwayland-scanner-bin">hyprwayland-scanner</primary>
          </indexterm>
        </listitem>
      </varlistentry>

    </variablelist>

  </sect2>

</sect1>
